dep_redis/__init__.py
pyproject.toml
tests/__init__.py
tests/test_module.py
dep_module_redis-2.7.29.dist-info/WHEEL
dep_module_redis-2.7.29.dist-info/METADATA
dep_module_redis-2.7.29.dist-info/RECORD
